{
  "nodePositions": [
    {
      "id": "Backend Development/Backend Development.md",
      "x": 130.81459045410156,
      "y": 49.43694305419922
    },
    {
      "id": "Backend Development/Go/Channels.md",
      "x": 427.8731689453125,
      "y": 182.4784393310547
    },
    {
      "id": "Backend Development/Go/Concurrency and Paralelism.md",
      "x": 555.9425659179688,
      "y": 19.8817195892334
    },
    {
      "id": "Backend Development/Go/Database-sql package.md",
      "x": 616.2008666992188,
      "y": 331.1713562011719
    },
    {
      "id": "Backend Development/Go/Documentation.md",
      "x": 633.4564208984375,
      "y": 212.9005126953125
    },
    {
      "id": "Backend Development/Go/Errors.md",
      "x": 762.0430297851562,
      "y": 49.795936584472656
    },
    {
      "id": "Backend Development/Go/Go Web/DELETE.md",
      "x": 490.9604797363281,
      "y": 530.6088256835938
    },
    {
      "id": "Backend Development/Go/Go Web/Go Web.md",
      "x": 384.327392578125,
      "y": 476.2873840332031
    },
    {
      "id": "Backend Development/Go/Go Web/Go in Spring Cloud Environment.md",
      "x": 608.0747680664062,
      "y": 556.2627563476562
    },
    {
      "id": "Backend Development/Go/Go Web/Go with OpenID.md",
      "x": 516.6898803710938,
      "y": 647.57421875
    },
    {
      "id": "Backend Development/Go/Go Web/PATCH.md",
      "x": 464.59454345703125,
      "y": 387.2816467285156
    },
    {
      "id": "Backend Development/Go/Go Web/POST.md",
      "x": 390.8214416503906,
      "y": 596.4122924804688
    },
    {
      "id": "Backend Development/Go/Go Web/PUT.md",
      "x": 283.9714660644531,
      "y": 541.8460693359375
    },
    {
      "id": "Backend Development/Go/Go Web/Repository.md",
      "x": 571.440673828125,
      "y": 442.0287780761719
    },
    {
      "id": "Backend Development/Go/Go Web/Web Context.md",
      "x": 302.2242126464844,
      "y": 388.87420654296875
    },
    {
      "id": "Backend Development/Go/Go.md",
      "x": 650.65966796875,
      "y": 94.53390502929688
    },
    {
      "id": "Backend Development/Go/Godotenv package.md",
      "x": 539.265380859375,
      "y": 138.37435913085938
    },
    {
      "id": "Backend Development/Go/IO and Files.md",
      "x": 727.6376342773438,
      "y": 287.1322937011719
    },
    {
      "id": "Backend Development/Go/Interfaces.md",
      "x": 744.8505859375,
      "y": 168.45123291015625
    },
    {
      "id": "Backend Development/Go/Marshall Function.md",
      "x": 573.7789306640625,
      "y": -98.69060516357422
    },
    {
      "id": "Backend Development/Go/Methods.md",
      "x": 856.2736206054688,
      "y": 124.01709747314453
    },
    {
      "id": "Backend Development/Go/Package-Oriented Design.md",
      "x": 667.2672729492188,
      "y": -23.765817642211914
    },
    {
      "id": "Backend Development/Go/Panic.md",
      "x": 521.961181640625,
      "y": 256.9606018066406
    },
    {
      "id": "Backend Development/Go/Pointers.md",
      "x": 462.1906433105469,
      "y": -54.865482330322266
    },
    {
      "id": "Backend Development/Go/Structures.md",
      "x": 839.0584716796875,
      "y": 242.73263549804688
    },
    {
      "id": "Backend Development/Go/Syntax.md",
      "x": 444.43426513671875,
      "y": 63.75071716308594
    },
    {
      "id": "Backend Development/Java/Collections/Browsing Collections.md",
      "x": -205.23973083496094,
      "y": 415.3003234863281
    },
    {
      "id": "Backend Development/Java/Collections/Collections.md",
      "x": -201.5042266845703,
      "y": 259.1342468261719
    },
    {
      "id": "Backend Development/Java/Collections/Operating Collections.md",
      "x": -112.39884948730469,
      "y": 339.3356018066406
    },
    {
      "id": "Backend Development/Java/Equality and Ordering.md",
      "x": -82.6330337524414,
      "y": 172.2348175048828
    },
    {
      "id": "Backend Development/Java/Exceptions/Custom Exceptions.md",
      "x": 61.89016342163086,
      "y": 489.73858642578125
    },
    {
      "id": "Backend Development/Java/Exceptions/Exception class.md",
      "x": 116.0676040649414,
      "y": 376.7146301269531
    },
    {
      "id": "Backend Development/Java/Exceptions/Exceptions.md",
      "x": -3.2553420066833496,
      "y": 389.02166748046875
    },
    {
      "id": "Backend Development/Java/Interfaces.md",
      "x": 36.55664825439453,
      "y": 158.45010375976562
    },
    {
      "id": "Backend Development/Java/Java.md",
      "x": -11.13086223602295,
      "y": 268.5606689453125
    },
    {
      "id": "Backend Development/Java/Object Class.md",
      "x": 108.05152893066406,
      "y": 254.81065368652344
    },
    {
      "id": "Backend Development/NodeJS/NodeJS.md",
      "x": 241.20323181152344,
      "y": 2.5813326835632324
    },
    {
      "id": "Computer System/Computer.md",
      "x": -280.7187805175781,
      "y": -325.5260009765625
    },
    {
      "id": "Computer System/Hardware/CPU.md",
      "x": -436.6221923828125,
      "y": -743.07421875
    },
    {
      "id": "Computer System/Hardware/Hardware.md",
      "x": -411.98870849609375,
      "y": -625.6331787109375
    },
    {
      "id": "Computer System/Hardware/Main Memory.md",
      "x": -303.7741394042969,
      "y": -443.2454528808594
    },
    {
      "id": "Computer System/Hardware/Memory.md",
      "x": -410.363525390625,
      "y": -498.13507080078125
    },
    {
      "id": "Computer System/Hardware/Secondary Memory.md",
      "x": -309.5536193847656,
      "y": -563.132568359375
    },
    {
      "id": "Computer System/Hardware/Von Neumann Architecture.md",
      "x": -322.60992431640625,
      "y": -705.6796875
    },
    {
      "id": "Computer System/Network/Addresses.md",
      "x": -792.509521484375,
      "y": -194.9540557861328
    },
    {
      "id": "Computer System/Network/Internet Protocol.md",
      "x": -639.6328735351562,
      "y": -345.6965637207031
    },
    {
      "id": "Computer System/Network/Network.md",
      "x": -753.6102294921875,
      "y": -308.4450378417969
    },
    {
      "id": "Computer System/Network/OSI Model.md",
      "x": -875.0762329101562,
      "y": -281.9622802734375
    },
    {
      "id": "Computer System/Network/Ports.md",
      "x": -836.1317749023438,
      "y": -395.4364318847656
    },
    {
      "id": "Computer System/Network/Routing.md",
      "x": -674.7705688476562,
      "y": -218.1190948486328
    },
    {
      "id": "Computer System/Software/Operating System.md",
      "x": -626.962158203125,
      "y": -601.16796875
    },
    {
      "id": "Computer System/Software/Remote Desktops and VM.md",
      "x": -543.3460083007812,
      "y": -687.207763671875
    },
    {
      "id": "Computer System/Software/Software.md",
      "x": -518.4044189453125,
      "y": -550.125244140625
    },
    {
      "id": "Database Administration/Database Administration.md",
      "x": -663.111572265625,
      "y": 96.30810546875
    },
    {
      "id": "Database Administration/Database Engines.md",
      "x": -763.7449340820312,
      "y": 21.569538116455078
    },
    {
      "id": "Database Administration/SQL/Alteration Functions.md",
      "x": -408.25341796875,
      "y": 469.6075744628906
    },
    {
      "id": "Database Administration/SQL/Best Practices.md",
      "x": -604.412841796875,
      "y": 401.69110107421875
    },
    {
      "id": "Database Administration/SQL/Excecution Order.md",
      "x": -447.638916015625,
      "y": 582.92431640625
    },
    {
      "id": "Database Administration/SQL/Indexes.md",
      "x": -526.0841674804688,
      "y": 492.2764892578125
    },
    {
      "id": "Database Administration/SQL/Joins.md",
      "x": -369.0276184082031,
      "y": 356.2326965332031
    },
    {
      "id": "Database Administration/SQL/SQL.md",
      "x": -486.7953796386719,
      "y": 378.96826171875
    },
    {
      "id": "Database Administration/SQL/Stored Procedures.md",
      "x": -568.9976806640625,
      "y": 287.02105712890625
    },
    {
      "id": "Database Administration/SQL/Views.md",
      "x": -451.16754150390625,
      "y": 264.4419860839844
    },
    {
      "id": "Frontend Development/Frontend Development.md",
      "x": -503.97479248046875,
      "y": -400.6797180175781
    },
    {
      "id": "Frontend Development/JavaScript/JavaScript.md",
      "x": -707.876220703125,
      "y": -510.2933349609375
    },
    {
      "id": "Frontend Development/JavaScript/Matrix.md",
      "x": -827.7274169921875,
      "y": -515.8956298828125
    },
    {
      "id": "Frontend Development/JavaScript/Sorting Methods.md",
      "x": -762.9636840820312,
      "y": -616.9076538085938
    },
    {
      "id": "Infrastructure Administration/Ansible.md",
      "x": 57.02432632446289,
      "y": -470.8627624511719
    },
    {
      "id": "Infrastructure Administration/Cloud/Cloud Databases.md",
      "x": 295.08026123046875,
      "y": -505.7780456542969
    },
    {
      "id": "Infrastructure Administration/Cloud/Cloud Storage.md",
      "x": 488.6726989746094,
      "y": -582.6122436523438
    },
    {
      "id": "Infrastructure Administration/Cloud/Cloud.md",
      "x": 369.93988037109375,
      "y": -599.4484252929688
    },
    {
      "id": "Infrastructure Administration/Cloud/Hybrid Cloud.md",
      "x": 253.15872192382812,
      "y": -626.548583984375
    },
    {
      "id": "Infrastructure Administration/Cloud/Load Balancer.md",
      "x": 525.7536010742188,
      "y": -696.7078247070312
    },
    {
      "id": "Infrastructure Administration/Cloud/Scalability, Fault Tolerance and Availability.md",
      "x": 407.0414123535156,
      "y": -713.3790893554688
    },
    {
      "id": "Infrastructure Administration/Cloud/Serverless.md",
      "x": 413.7646789550781,
      "y": -487.8896484375
    },
    {
      "id": "Infrastructure Administration/Configuration Management.md",
      "x": -5.272141933441162,
      "y": -669.1292114257812
    },
    {
      "id": "Infrastructure Administration/Docker.md",
      "x": -122.54764556884766,
      "y": -643.9226684570312
    },
    {
      "id": "Infrastructure Administration/Git.md",
      "x": -148.5226287841797,
      "y": -526.775146484375
    },
    {
      "id": "Infrastructure Administration/GitHub.md",
      "x": 83.1253433227539,
      "y": -587.9800415039062
    },
    {
      "id": "Infrastructure Administration/Infrastructure Administration.md",
      "x": -31.29414176940918,
      "y": -552.035400390625
    },
    {
      "id": "Infrastructure Administration/Shell Scripting/Bash Commands.md",
      "x": 139.07357788085938,
      "y": -338.77001953125
    },
    {
      "id": "Infrastructure Administration/Shell Scripting/Bash Scripting.md",
      "x": 64.2408676147461,
      "y": -244.96253967285156
    },
    {
      "id": "Infrastructure Administration/Shell Scripting/Shell Scripting.md",
      "x": 20.410552978515625,
      "y": -356.6328125
    },
    {
      "id": "Infrastructure Administration/Working Environments.md",
      "x": -67.95586395263672,
      "y": -437.8196105957031
    },
    {
      "id": "Programming Theory/Algorithm.md",
      "x": -520.3307495117188,
      "y": -99.35598754882812
    },
    {
      "id": "Programming Theory/Computational Complexity.md",
      "x": -185.76690673828125,
      "y": -58.73995590209961
    },
    {
      "id": "Programming Theory/Computational Thinking.md",
      "x": -282.4254455566406,
      "y": -129.7926483154297
    },
    {
      "id": "Programming Theory/Documentation.md",
      "x": -278.2724914550781,
      "y": 162.29908752441406
    },
    {
      "id": "Programming Theory/Domain-Driven Design.md",
      "x": -447.51171875,
      "y": -4.1210150718688965
    },
    {
      "id": "Programming Theory/Frameworks.md",
      "x": -172.7211151123047,
      "y": -177.89163208007812
    },
    {
      "id": "Programming Theory/IDEs.md",
      "x": -355.2144470214844,
      "y": -225.1290283203125
    },
    {
      "id": "Programming Theory/Libraries.md",
      "x": -231.8303985595703,
      "y": 51.77915954589844
    },
    {
      "id": "Programming Theory/Object-Oriented Programming/Abstract Class.md",
      "x": -166.5237274169922,
      "y": 694.091796875
    },
    {
      "id": "Programming Theory/Object-Oriented Programming/Aggregation Relationship.md",
      "x": -236.01815795898438,
      "y": 889.8272705078125
    },
    {
      "id": "Programming Theory/Object-Oriented Programming/Association Relationship.md",
      "x": -52.88340759277344,
      "y": 735.14501953125
    },
    {
      "id": "Programming Theory/Object-Oriented Programming/Composition Relationship.md",
      "x": -213.97259521484375,
      "y": 1007.787353515625
    },
    {
      "id": "Programming Theory/Object-Oriented Programming/Design Patterns/Chain of Responsibility Pattern.md",
      "x": 399.65899658203125,
      "y": 973.6070556640625
    },
    {
      "id": "Programming Theory/Object-Oriented Programming/Design Patterns/Composite Pattern.md",
      "x": 197.41378784179688,
      "y": 844.6954956054688
    },
    {
      "id": "Programming Theory/Object-Oriented Programming/Design Patterns/Design Patterns.md",
      "x": 192.1265869140625,
      "y": 964.3912353515625
    },
    {
      "id": "Programming Theory/Object-Oriented Programming/Design Patterns/Facade Pattern.md",
      "x": 202.6845245361328,
      "y": 724.941650390625
    },
    {
      "id": "Programming Theory/Object-Oriented Programming/Design Patterns/Factory Pattern.md",
      "x": 293.268798828125,
      "y": 1028.94287109375
    },
    {
      "id": "Programming Theory/Object-Oriented Programming/Design Patterns/Flyweight Pattern.md",
      "x": 298.5273742675781,
      "y": 909.1656494140625
    },
    {
      "id": "Programming Theory/Object-Oriented Programming/Design Patterns/Observer Pattern.md",
      "x": 186.84982299804688,
      "y": 1084.2244873046875
    },
    {
      "id": "Programming Theory/Object-Oriented Programming/Design Patterns/Proxy Pattern.md",
      "x": 404.9602966308594,
      "y": 853.7760620117188
    },
    {
      "id": "Programming Theory/Object-Oriented Programming/Design Patterns/Singleton Pattern.md",
      "x": 303.81707763671875,
      "y": 789.3176879882812
    },
    {
      "id": "Programming Theory/Object-Oriented Programming/Design Patterns/State Pattern.md",
      "x": 90.9682846069336,
      "y": 900.033935546875
    },
    {
      "id": "Programming Theory/Object-Oriented Programming/Design Patterns/Strategy Pattern.md",
      "x": 85.68600463867188,
      "y": 1019.8088989257812
    },
    {
      "id": "Programming Theory/Object-Oriented Programming/Design Patterns/Template Method Pattern.md",
      "x": 96.27977752685547,
      "y": 780.2591552734375
    },
    {
      "id": "Programming Theory/Object-Oriented Programming/Dynamic Binding.md",
      "x": -100.68962097167969,
      "y": 1047.40771484375
    },
    {
      "id": "Programming Theory/Object-Oriented Programming/Inheritance.md",
      "x": -144.8983917236328,
      "y": 811.9276123046875
    },
    {
      "id": "Programming Theory/Object-Oriented Programming/Method Signature.md",
      "x": -30.862905502319336,
      "y": 853.0670776367188
    },
    {
      "id": "Programming Theory/Object-Oriented Programming/Object-Oriented Programming.md",
      "x": -123.02027130126953,
      "y": 929.7424926757812
    },
    {
      "id": "Programming Theory/Object-Oriented Programming/Overloading.md",
      "x": -257.89654541015625,
      "y": 771.8668212890625
    },
    {
      "id": "Programming Theory/Object-Oriented Programming/Polymorphism.md",
      "x": -349.0368347167969,
      "y": 849.859130859375
    },
    {
      "id": "Programming Theory/Object-Oriented Programming/Protected Attribute.md",
      "x": -327.0416564941406,
      "y": 967.8092041015625
    },
    {
      "id": "Programming Theory/Parametric Programming.md",
      "x": -493.7933654785156,
      "y": 106.34539794921875
    },
    {
      "id": "Programming Theory/Programming Language.md",
      "x": -401.36181640625,
      "y": -114.5206527709961
    },
    {
      "id": "Programming Theory/Programming Paradigms.md",
      "x": -374.81982421875,
      "y": 91.31348419189453
    },
    {
      "id": "Programming Theory/Programming Theory.md",
      "x": -328.4747009277344,
      "y": -19.253013610839844
    },
    {
      "id": "Security/Active and Passive Security.md",
      "x": 324.21636962890625,
      "y": -1010.285888671875
    },
    {
      "id": "Security/Authentication.md",
      "x": 87.69732666015625,
      "y": -798.8475341796875
    },
    {
      "id": "Security/Bugs and Vulnerabilities.md",
      "x": 327.52935791015625,
      "y": -803.0148315429688
    },
    {
      "id": "Security/Cyber Threats.md",
      "x": 386.28521728515625,
      "y": -907.619873046875
    },
    {
      "id": "Security/Cybersecurity.md",
      "x": 26.031625747680664,
      "y": -901.7683715820312
    },
    {
      "id": "Security/Information.md",
      "x": 145.87635803222656,
      "y": -903.7169189453125
    },
    {
      "id": "Security/Middleware.md",
      "x": 207.57376098632812,
      "y": -800.7705078125
    },
    {
      "id": "Security/Security Measures.md",
      "x": 204.2572784423828,
      "y": -1008.6530151367188
    },
    {
      "id": "Security/Security.md",
      "x": 265.7105407714844,
      "y": -905.6718139648438
    },
    {
      "id": "Security/VPN and Tor.md",
      "x": 84.34518432617188,
      "y": -1006.635986328125
    },
    {
      "id": "Templates/DefaultTemplate.md",
      "x": -465.1602478027344,
      "y": -900.141845703125
    },
    {
      "id": "Testing/Debugging.md",
      "x": 614.8081665039062,
      "y": -423.7366027832031
    },
    {
      "id": "Testing/Defects.md",
      "x": 704.991943359375,
      "y": -200.74501037597656
    },
    {
      "id": "Testing/Dynamic Testing.md",
      "x": 982.6686401367188,
      "y": -378.130615234375
    },
    {
      "id": "Testing/Implementation Stage.md",
      "x": 882.30126953125,
      "y": -80.4028091430664
    },
    {
      "id": "Testing/JUnit.md",
      "x": 541.0349731445312,
      "y": -329.1295166015625
    },
    {
      "id": "Testing/Smoke and Regression Testing.md",
      "x": 908.6192626953125,
      "y": -284.3582458496094
    },
    {
      "id": "Testing/Software Testing Lifecycle.md",
      "x": 659.6768798828125,
      "y": -312.5160827636719
    },
    {
      "id": "Testing/Static Testing.md",
      "x": 688.8629760742188,
      "y": -518.1135864257812
    },
    {
      "id": "Testing/Test Cases.md",
      "x": 956.6396484375,
      "y": -174.51731872558594
    },
    {
      "id": "Testing/Test Driven Development.md",
      "x": 834.9443969726562,
      "y": -190.43995666503906
    },
    {
      "id": "Testing/Test Levels.md",
      "x": 852.23779296875,
      "y": -389.8124084472656
    },
    {
      "id": "Testing/Test Organization by Workspace.md",
      "x": 586.2359619140625,
      "y": -217.91563415527344
    },
    {
      "id": "Testing/Test Types.md",
      "x": 733.4993896484375,
      "y": -406.89422607421875
    },
    {
      "id": "Testing/Testing Techniques.md",
      "x": 926.2647705078125,
      "y": -483.9239807128906
    },
    {
      "id": "Testing/Testing.md",
      "x": 778.1967163085938,
      "y": -295.68280029296875
    },
    {
      "id": "Testing/Unit Testing.md",
      "x": 807.5722045898438,
      "y": -501.15777587890625
    },
    {
      "id": "Testing/Use Cases.md",
      "x": 763.08447265625,
      "y": -94.99018096923828
    },
    {
      "id": "Backend Development/ORM.md",
      "x": 145.4528045654297,
      "y": -69.70296478271484
    },
    {
      "id": "Backend Development/Parameters.md",
      "x": 35.03815460205078,
      "y": -22.767818450927734
    },
    {
      "id": "Database Administration/Data Analytics/Data Analytics.md",
      "x": -803.157958984375,
      "y": 551.2958984375
    },
    {
      "id": "Database Administration/Data Analytics/ETL.md",
      "x": -994.37353515625,
      "y": 457.5372314453125
    },
    {
      "id": "Database Administration/Data Analytics/Data Warehouse.md",
      "x": -936.5657348632812,
      "y": 352.40924072265625
    },
    {
      "id": "Database Administration/Data Analytics/Data Lake.md",
      "x": -877.8956298828125,
      "y": 247.67971801757812
    },
    {
      "id": "Database Administration/Data Analytics/Power BI.md",
      "x": -860.5192260742188,
      "y": 656.5573120117188
    },
    {
      "id": "Database Administration/Data Analytics/KPI.md",
      "x": -683.2714233398438,
      "y": 549.9934692382812
    },
    {
      "id": "Database Administration/Data Analytics/OKR.md",
      "x": -740.5934448242188,
      "y": 655.3717041015625
    },
    {
      "id": "Database Administration/Data Analytics/Dimensions.md",
      "x": -874.5582275390625,
      "y": 455.1929931640625
    },
    {
      "id": "Database Administration/Data Analytics/Data Classifications.md",
      "x": -744.64990234375,
      "y": 446.5810241699219
    },
    {
      "id": "Database Administration/Data Analytics/Data Manipulation.md",
      "x": -699.032470703125,
      "y": 328.5139465332031
    },
    {
      "id": "Database Administration/Data Analytics/Data Modeling.md",
      "x": -816.6956176757812,
      "y": 350.5604553222656
    },
    {
      "id": "Database Administration/Data Analytics/Data Exploration.md",
      "x": -931.9747314453125,
      "y": 560.2620849609375
    },
    {
      "id": "Pending ClickUp.md",
      "x": -279.18743896484375,
      "y": -923.3765869140625
    }
  ],
  "automaticallyRestoreNodePositions": true
}